{
 "files": [
  {
   "name": ".",
   "ftype": "dir",
   "chksum_type": null,
   "chksum_sha256": null,
   "format": 1
  },
  {
   "name": ".cache",
   "ftype": "dir",
   "chksum_type": null,
   "chksum_sha256": null,
   "format": 1
  },
  {
   "name": ".cache/collections",
   "ftype": "dir",
   "chksum_type": null,
   "chksum_sha256": null,
   "format": 1
  },
  {
   "name": ".cache/collections/ansible_collections",
   "ftype": "dir",
   "chksum_type": null,
   "chksum_sha256": null,
   "format": 1
  },
  {
   "name": ".cache/collections/ansible_collections/operator_sdk",
   "ftype": "dir",
   "chksum_type": null,
   "chksum_sha256": null,
   "format": 1
  },
  {
   "name": ".cache/collections/ansible_collections/operator_sdk/util",
   "ftype": "dir",
   "chksum_type": null,
   "chksum_sha256": null,
   "format": 1
  },
  {
   "name": "tests",
   "ftype": "dir",
   "chksum_type": null,
   "chksum_sha256": null,
   "format": 1
  },
  {
   "name": "tests/sanity",
   "ftype": "dir",
   "chksum_type": null,
   "chksum_sha256": null,
   "format": 1
  },
  {
   "name": "tests/sanity/ignore-2.9.txt",
   "ftype": "file",
   "chksum_type": "sha256",
   "chksum_sha256": "a52be73d4d33b49f5428f90f6248645278f8778ea34edff3243595198e2e84be",
   "format": 1
  },
  {
   "name": ".github",
   "ftype": "dir",
   "chksum_type": null,
   "chksum_sha256": null,
   "format": 1
  },
  {
   "name": ".github/workflows",
   "ftype": "dir",
   "chksum_type": null,
   "chksum_sha256": null,
   "format": 1
  },
  {
   "name": ".github/workflows/ci.yml",
   "ftype": "file",
   "chksum_type": "sha256",
   "chksum_sha256": "e3986aefa68ac6f118d5002fec923142a391bba221cf82961b7495753f3fbceb",
   "format": 1
  },
  {
   "name": "LICENSE",
   "ftype": "file",
   "chksum_type": "sha256",
   "chksum_sha256": "c71d239df91726fc519c6eb72d318ec65820627232b2f796219e87dcf35d0ab4",
   "format": 1
  },
  {
   "name": "README.md",
   "ftype": "file",
   "chksum_type": "sha256",
   "chksum_sha256": "33d3158c15438263f1811e0186cca9b6734a3a3fddcea88338c8d742fcba0e88",
   "format": 1
  },
  {
   "name": ".yamllint",
   "ftype": "file",
   "chksum_type": "sha256",
   "chksum_sha256": "13e808f3ce12e7a20a091bdb65fc1c2a5802dfaad85527639e62bcce84f8efb8",
   "format": 1
  },
  {
   "name": "Makefile",
   "ftype": "file",
   "chksum_type": "sha256",
   "chksum_sha256": "a6da7e486cad37b37e9ac6980def0aa8f58fb59f58ede453ad44f9ec56dd8b46",
   "format": 1
  },
  {
   "name": ".gitignore",
   "ftype": "file",
   "chksum_type": "sha256",
   "chksum_sha256": "1e87175a024a4cf4bf7b3a5fa623d046351a591d5cee549d8ca8c30ec669a013",
   "format": 1
  },
  {
   "name": "plugins",
   "ftype": "dir",
   "chksum_type": null,
   "chksum_sha256": null,
   "format": 1
  },
  {
   "name": "plugins/module_utils",
   "ftype": "dir",
   "chksum_type": null,
   "chksum_sha256": null,
   "format": 1
  },
  {
   "name": "plugins/module_utils/args_common.py",
   "ftype": "file",
   "chksum_type": "sha256",
   "chksum_sha256": "54be5671d313ffbf71ad26a0ac62fa45e19c86926e69c25ad7d323aa1cd36ddc",
   "format": 1
  },
  {
   "name": "plugins/module_utils/__init__.py",
   "ftype": "file",
   "chksum_type": "sha256",
   "chksum_sha256": "e3b0c44298fc1c149afbf4c8996fb92427ae41e4649b934ca495991b7852b855",
   "format": 1
  },
  {
   "name": "plugins/doc_fragments",
   "ftype": "dir",
   "chksum_type": null,
   "chksum_sha256": null,
   "format": 1
  },
  {
   "name": "plugins/doc_fragments/osdk_auth_options.py",
   "ftype": "file",
   "chksum_type": "sha256",
   "chksum_sha256": "2b31547ebe723a03757e6802e4b918bca4eeb25b5088eb1396e45048a37608f3",
   "format": 1
  },
  {
   "name": "plugins/doc_fragments/osdk_name_options.py",
   "ftype": "file",
   "chksum_type": "sha256",
   "chksum_sha256": "dee3beaf7f0535a2767536743009d9f8fd83f7ca9f602c9404fcfc392e859b82",
   "format": 1
  },
  {
   "name": "plugins/doc_fragments/__init__.py",
   "ftype": "file",
   "chksum_type": "sha256",
   "chksum_sha256": "e3b0c44298fc1c149afbf4c8996fb92427ae41e4649b934ca495991b7852b855",
   "format": 1
  },
  {
   "name": "plugins/README.md",
   "ftype": "file",
   "chksum_type": "sha256",
   "chksum_sha256": "58b5a167904c91786df167dd097ab76aed73ffba6cc746a3624c2a5bbf62ef6f",
   "format": 1
  },
  {
   "name": "plugins/modules",
   "ftype": "dir",
   "chksum_type": null,
   "chksum_sha256": null,
   "format": 1
  },
  {
   "name": "plugins/modules/k8s_status.py",
   "ftype": "file",
   "chksum_type": "sha256",
   "chksum_sha256": "218e9e13c15dcab58022286fce01023db88ccd66260d2442ceb636d12c254145",
   "format": 1
  },
  {
   "name": "plugins/modules/requeue_after.py",
   "ftype": "file",
   "chksum_type": "sha256",
   "chksum_sha256": "ddb8978933a27ff509efba33308b05e7440c7606a9df8c4ba82b40ee40fd6c11",
   "format": 1
  },
  {
   "name": "setup.cfg",
   "ftype": "file",
   "chksum_type": "sha256",
   "chksum_sha256": "125fefc5c9470b8e72cffc06937c30e2bc073f4ca6c1a593f131a6e1fd76edf2",
   "format": 1
  },
  {
   "name": "molecule",
   "ftype": "dir",
   "chksum_type": null,
   "chksum_sha256": null,
   "format": 1
  },
  {
   "name": "molecule/default",
   "ftype": "dir",
   "chksum_type": null,
   "chksum_sha256": null,
   "format": 1
  },
  {
   "name": "molecule/default/molecule.yml",
   "ftype": "file",
   "chksum_type": "sha256",
   "chksum_sha256": "74541fd07e7728652e4747ed1ccc7c11a015eb09d063532e0f61635e5ca8c1c4",
   "format": 1
  },
  {
   "name": "molecule/default/tasks",
   "ftype": "dir",
   "chksum_type": null,
   "chksum_sha256": null,
   "format": 1
  },
  {
   "name": "molecule/default/tasks/advanced_usage.yml",
   "ftype": "file",
   "chksum_type": "sha256",
   "chksum_sha256": "5e72803f88e7ba5cbd6cae193bd01ee61b69bb5ff1434814ca369434898e5f06",
   "format": 1
  },
  {
   "name": "molecule/default/tasks/doc_examples.yml",
   "ftype": "file",
   "chksum_type": "sha256",
   "chksum_sha256": "1573f2e62096c83012a09f55bc406d1fc8832d6e473b1391eff9ffbdb86457e6",
   "format": 1
  },
  {
   "name": "molecule/default/tasks/failure_modes.yml",
   "ftype": "file",
   "chksum_type": "sha256",
   "chksum_sha256": "d23d0e8b0728702b08086eab3756e2292b98c7c9a422d8c860b8556e5c2d5633",
   "format": 1
  },
  {
   "name": "molecule/default/converge.yml",
   "ftype": "file",
   "chksum_type": "sha256",
   "chksum_sha256": "a7fa23422fb8195f87621c27ae783a71964e74ff1a8debe81b6dc715eda5ae98",
   "format": 1
  },
  {
   "name": "molecule/default/files",
   "ftype": "dir",
   "chksum_type": null,
   "chksum_sha256": null,
   "format": 1
  },
  {
   "name": "molecule/default/files/crd.yaml",
   "ftype": "file",
   "chksum_type": "sha256",
   "chksum_sha256": "e8e1281aa85321e142069c1948a15805cc49a12a7f9203f9ae374fd2a701a04a",
   "format": 1
  }
 ],
 "format": 1
}